rbd.py
setup.py
rubberduck/__init__.py
rubberduck/search_result.py
rubberduck.egg-info/PKG-INFO
rubberduck.egg-info/SOURCES.txt
rubberduck.egg-info/dependency_links.txt
rubberduck.egg-info/entry_points.txt
rubberduck.egg-info/requires.txt
rubberduck.egg-info/top_level.txt